ctgutils/ctgFuncts/__init__.py
ctgutils/ctgFuncts/club38.py
ctgutils/ctgFuncts/ctg_classes.py
ctgutils/ctgFuncts/ctg_effectif.py
ctgutils/ctgFuncts/ctg_plot.py
ctgutils/ctgFuncts/ctg_synthese.py
ctgutils/ctgFuncts/ctg_tools.py
ctgutils/ctgFuncts/ctg_utils.py
ctgutils/ctgFuncts/pagesynthese.py
ctgutils/ctggui/__init__.py
ctgutils/ctggui/guiglobals.py
ctgutils/ctggui/page_effectif.py
ctgutils/ctggui/pageclasses.py
ctgutils/ctggui/pagedivers.py
ctgutils/ctggui/pagesorties.py
ctgutils/ctggui/pagesynthese.py
ctgutils/ctggui/pagetendance.py
ctgutils/ctggui/useful_functions.py
CTG_Utils-1.2.2.dist-info/LICENSE
CTG_Utils-1.2.2.dist-info/METADATA
CTG_Utils-1.2.2.dist-info/WHEEL
CTG_Utils-1.2.2.dist-info/top_level.txt
CTG_Utils-1.2.2.dist-info/RECORD
